{
  "kind": "collectionType",
  "collectionName": "students",
  "info": {
    "singularName": "student",
    "pluralName": "students",
    "displayName": "Student",
    "description": ""
  },
  "options": {
    "draftAndPublish": true
  },
  "pluginOptions": {},
  "attributes": {
    "name": {
      "type": "string",
      "required": true,
      "unique": true
    },
    "no": {
      "type": "integer"
    },
    "Math": {
      "type": "decimal"
    },
    "Biology": {
      "type": "decimal"
    },
    "English": {
      "type": "decimal"
    },
    "Physics": {
      "type": "decimal"
    },
    "Chemistry": {
      "type": "decimal"
    }
  }
}
